<annotation>
	<folder>f</folder>
	<filename>f_f01004_20190327T213609_11.jpg</filename>
	<path>C:\Users\serkan\Desktop\windows_v1.6.0\chickpea_images\f\f01004_20190327T213609_11.jpg</path>
	<source>
		<database>Unknown</database>
	</source>
	<size>
		<width>768</width>
		<height>432</height>
		<depth>3</depth>
	</size>
	<segmented>0</segmented>
	<object>
		<name>chickpea</name>
		<pose>Unspecified</pose>
		<truncated>0</truncated>
		<difficult>0</difficult>
		<bndbox>
			<xmin>446</xmin>
			<ymin>142</ymin>
			<xmax>550</xmax>
			<ymax>232</ymax>
		</bndbox>
	</object>
	<object>
		<name>chickpea</name>
		<pose>Unspecified</pose>
		<truncated>0</truncated>
		<difficult>0</difficult>
		<bndbox>
			<xmin>602</xmin>
			<ymin>322</ymin>
			<xmax>646</xmax>
			<ymax>388</ymax>
		</bndbox>
	</object>
	<object>
		<name>chickpea</name>
		<pose>Unspecified</pose>
		<truncated>0</truncated>
		<difficult>0</difficult>
		<bndbox>
			<xmin>365</xmin>
			<ymin>153</ymin>
			<xmax>452</xmax>
			<ymax>226</ymax>
		</bndbox>
	</object>
	<object>
		<name>chickpea</name>
		<pose>Unspecified</pose>
		<truncated>0</truncated>
		<difficult>0</difficult>
		<bndbox>
			<xmin>292</xmin>
			<ymin>155</ymin>
			<xmax>363</xmax>
			<ymax>226</ymax>
		</bndbox>
	</object>
	<object>
		<name>chickpea</name>
		<pose>Unspecified</pose>
		<truncated>0</truncated>
		<difficult>0</difficult>
		<bndbox>
			<xmin>214</xmin>
			<ymin>175</ymin>
			<xmax>293</xmax>
			<ymax>256</ymax>
		</bndbox>
	</object>
	<object>
		<name>chickpea</name>
		<pose>Unspecified</pose>
		<truncated>0</truncated>
		<difficult>0</difficult>
		<bndbox>
			<xmin>250</xmin>
			<ymin>345</ymin>
			<xmax>318</xmax>
			<ymax>402</ymax>
		</bndbox>
	</object>
</annotation>
