<annotation>
	<folder>f</folder>
	<filename>f_f01007_20190327T214304_8.jpg</filename>
	<path>C:\Users\serkan\Desktop\windows_v1.6.0\chickpea_images\f\f01007_20190327T214304_8.jpg</path>
	<source>
		<database>Unknown</database>
	</source>
	<size>
		<width>768</width>
		<height>432</height>
		<depth>3</depth>
	</size>
	<segmented>0</segmented>
	<object>
		<name>chickpea</name>
		<pose>Unspecified</pose>
		<truncated>0</truncated>
		<difficult>0</difficult>
		<bndbox>
			<xmin>476</xmin>
			<ymin>224</ymin>
			<xmax>550</xmax>
			<ymax>299</ymax>
		</bndbox>
	</object>
	<object>
		<name>chickpea</name>
		<pose>Unspecified</pose>
		<truncated>0</truncated>
		<difficult>0</difficult>
		<bndbox>
			<xmin>414</xmin>
			<ymin>89</ymin>
			<xmax>485</xmax>
			<ymax>166</ymax>
		</bndbox>
	</object>
	<object>
		<name>chickpea</name>
		<pose>Unspecified</pose>
		<truncated>0</truncated>
		<difficult>0</difficult>
		<bndbox>
			<xmin>356</xmin>
			<ymin>92</ymin>
			<xmax>401</xmax>
			<ymax>154</ymax>
		</bndbox>
	</object>
	<object>
		<name>chickpea</name>
		<pose>Unspecified</pose>
		<truncated>0</truncated>
		<difficult>0</difficult>
		<bndbox>
			<xmin>325</xmin>
			<ymin>248</ymin>
			<xmax>378</xmax>
			<ymax>309</ymax>
		</bndbox>
	</object>
	<object>
		<name>chickpea</name>
		<pose>Unspecified</pose>
		<truncated>0</truncated>
		<difficult>0</difficult>
		<bndbox>
			<xmin>108</xmin>
			<ymin>251</ymin>
			<xmax>208</xmax>
			<ymax>317</ymax>
		</bndbox>
	</object>
</annotation>
