<annotation>
	<folder>g</folder>
	<filename>g_f01001_20190327T234136_10.jpg</filename>
	<path>C:\Sunita\Desktop-ICRISAT\Proposals\ECR Award-2018\CZU\chickpea_images_plant count Serkan\g\f01001_20190327T234136_10.jpg</path>
	<source>
		<database>Unknown</database>
	</source>
	<size>
		<width>768</width>
		<height>432</height>
		<depth>3</depth>
	</size>
	<segmented>0</segmented>
	<object>
		<name>chickpea</name>
		<pose>Unspecified</pose>
		<truncated>0</truncated>
		<difficult>0</difficult>
		<bndbox>
			<xmin>138</xmin>
			<ymin>225</ymin>
			<xmax>215</xmax>
			<ymax>325</ymax>
		</bndbox>
	</object>
	<object>
		<name>chickpea</name>
		<pose>Unspecified</pose>
		<truncated>0</truncated>
		<difficult>0</difficult>
		<bndbox>
			<xmin>145</xmin>
			<ymin>84</ymin>
			<xmax>212</xmax>
			<ymax>153</ymax>
		</bndbox>
	</object>
	<object>
		<name>chickpea</name>
		<pose>Unspecified</pose>
		<truncated>0</truncated>
		<difficult>0</difficult>
		<bndbox>
			<xmin>228</xmin>
			<ymin>108</ymin>
			<xmax>327</xmax>
			<ymax>198</ymax>
		</bndbox>
	</object>
	<object>
		<name>chickpea</name>
		<pose>Unspecified</pose>
		<truncated>0</truncated>
		<difficult>0</difficult>
		<bndbox>
			<xmin>399</xmin>
			<ymin>85</ymin>
			<xmax>492</xmax>
			<ymax>171</ymax>
		</bndbox>
	</object>
	<object>
		<name>chickpea</name>
		<pose>Unspecified</pose>
		<truncated>0</truncated>
		<difficult>0</difficult>
		<bndbox>
			<xmin>515</xmin>
			<ymin>95</ymin>
			<xmax>580</xmax>
			<ymax>198</ymax>
		</bndbox>
	</object>
	<object>
		<name>chickpea</name>
		<pose>Unspecified</pose>
		<truncated>0</truncated>
		<difficult>0</difficult>
		<bndbox>
			<xmin>489</xmin>
			<ymin>278</ymin>
			<xmax>600</xmax>
			<ymax>363</ymax>
		</bndbox>
	</object>
	<object>
		<name>chickpea</name>
		<pose>Unspecified</pose>
		<truncated>0</truncated>
		<difficult>0</difficult>
		<bndbox>
			<xmin>402</xmin>
			<ymin>228</ymin>
			<xmax>487</xmax>
			<ymax>352</ymax>
		</bndbox>
	</object>
	<object>
		<name>chickpea</name>
		<pose>Unspecified</pose>
		<truncated>0</truncated>
		<difficult>0</difficult>
		<bndbox>
			<xmin>241</xmin>
			<ymin>215</ymin>
			<xmax>342</xmax>
			<ymax>310</ymax>
		</bndbox>
	</object>
</annotation>
